Metadata-Version: 1.2
Name: intake-avro
Version: 0.2.0
Summary: Intake avro plugin
Home-page: https://github.com/ContinuumIO/intake-avro
Maintainer: Martin Durant
Maintainer-email: martin.durant@utoronto.ca
License: BSD
Platform: UNKNOWN
